<?xml version="1.0" encoding="utf-8" standalone="yes"?>
<toggleable_menu name="profile_overflow_menu">
	<menu_item_call label="Compartir" name="share"/>
	<menu_item_call label="Llamar" name="call"/>
	<menu_item_call label="Copiar nombre" name="copy_name_to_clipboard"/>
	<menu_item_call label="Copiar URI" name="copy_uri_to_clipboard"/>
	<menu_item_call label="Copiar UUID" name="copy_key_to_clipboard"/>
	<menu_item_call label="Expulsar" name="kick"/>
	<menu_item_call label="Congelar" name="freeze"/>
	<menu_item_call label="Descongelar" name="unfreeze"/>
	<menu_item_call label="CSR" name="csr"/>
</toggleable_menu>
