<?xml version="1.0" encoding="utf-8" standalone="yes" ?>
<floater name="phototools" title="Фотоінструменти">
	<tab_container name="tabs">
		<panel name="EnvironmentTab" label="EnvironmentWednesday">
			<panel name="PT_WL_Settings">
				<text name="T_WL_Settings">
					Налаштування навколишнього середовища
				</text>
			</panel>

			<panel name="P_WL_Settings">
				<check_box name="WindLightUseAtmosShaders" label="Атмосферні шейдери"
				 tool_tip="Це дозволить використовувати повну функціональність Розширеного Навколишнього Середовища (Атмосферні шейдери)."/>
			</panel>

			<panel name="P_WL_Sky_Water">
				<text name="WL Sky" tool_tip="Предустановлення неба для вашого довкілля.">
					Небо
				</text>
				<text name="WL Water" tool_tip="Налаштування води для вашого навколишнього середовища.">
					вода
				</text>
				<text name="Day Cycle" tool_tip="Предустановка циклу дня для вашого довкілля.">
					Цикл Дня
				</text>
				<button name="btn_personal_lighting" label="Особисте Освітлення..."/>
				<button name="ResetToRegionDefault" tool_tip="Скинути параметри за замовчуванням у регіоні."/>
				<button label="Пауза Хмар" name="PauseClouds" tool_tip="Припиняє анімацію хмар"/>
			</panel>

			<panel name="P_Q_Windlights">
				<text name="T_Q_Windlights">
					Швидке налаштування
				</text>
				<button name="Sunrise" label="Рассвет"/>
				<button name="Noon" label="Полдень"/>
				<button name="Sunset" label="Закат"/>
				<button name="Midnight" label="Північ"/>
				<button name="Revert to Region Default" label="Час регіону"/>
			</panel>

			<panel name="P_WL_Presets">
				<text name="T_WL_Presets" tool_tip="Клацніть елемент нижче, щоб створити нове попереднє встановлення або змінити існуюче.">
					Передустановки
				</text>
				<button name="new_sky_preset" label="Нове Небо"/>
				<button name="edit_sky_preset" label="Правити Небо"/>
				<button name="new_water_preset" label="Нова Вода"/>
				<button name="edit_water_preset" label="Правити Воду"/>
			</panel>

			<panel name="P_W_Reflections">
				<text name="T_W_Reflections">
					Налаштування Відображення Води
				</text>
			</panel>

			<panel name="P_W_R_Types">
				<text name="T_W_R_Types" tool_tip="Визначає, що відображатиметься у воді.">
					Тип
				</text>
				<combo_box name="Віддзеркалення">
					<combo_box.item name="0" label="Мінімум"/>
					<combo_box.item name="1" label="Земля та дерева"/>
					<combo_box.item name="2" label="Всі статичні об'єкти"/>
					<combo_box.item name="3" label="Усі аватари та об'єкти"/>
					<combo_box.item name="4" label="Все"/>
				</combo_box>
			</panel>

			<panel name="P_R_Res">
				<text name="T_R_Res" tool_tip="Визначає роздільну здатність/якість відображення води. Якщо для параметрів роздільної здатності встановлено значення «Дуже добре» або вище, ви також повинні включити «Розширена модель освітлення» на вкладці «Світло».">
					Дозвіл
				</text>
				<combo_box name="ReflectionRescombo">
					<combo_box.item name="0" label="Прийнятно"/>
					<combo_box.item name="1" label="Добре"/>
					<combo_box.item name="2" label="Дуже добре - Потрібно ввімкнути «Розширена модель освітлення» (вкладка «Світло»)"/>
					<combo_box.item name="3" label="Відмінно - Потрібно увімкнути «Розширена модель освітлення» (вкладка «Світло»)"/>
					<combo_box.item name="4" label="Визначне - Потрібно увімкнути «Розширена модель освітлення» (вкладка «Світло»)"/>
					<combo_box.item name="5" label="Як живе - Потрібно увімкнути «Розширена модель освітлення» (вкладка «Світло»)"/>
				</combo_box>
				<check_box name="TransparentWater" label="Прозора Вода" tool_tip="Відображає воду прозорою. Відключення робить воду непрозорою із застосуванням простої текстури."/>
			</panel>
		</panel>

		<panel name="P_Lighting" label="Сторінка">
			<panel name="PT_Light_Shadows">
				<text name="T_Light_Shadows">
					Налаштування Світла та Тіней
				</text>
			</panel>

			<panel name="P_L_S_Settings">
				<check_box name="RenderDeferred" label="Розширена модель освітлення"
				 tool_tip="Це дозволить створити тіні від Сонця та Місяця, а також від зовнішніх джерел світла. Це також дозволить вам увімкнути Глибину Різкості та інші графічні функції. В основному вам потрібно включити це, щоб побачити більшу частину «смаків» у світі. Якщо ви не можете увімкнути цю функцію або побачити її ефект, спочатку переконайтеся, що Атмосферні шейдери включені на вкладці «Окр.среда»."/>
				<check_box name="LocalLights" label="Увімкнути все локальне освітлення"
				 tool_tip="Це включить усі вогні у світі. Якщо ви вимкнете цю функцію, світло від Сонця/Місяця, як і раніше, буде відображатися. Корисно, якщо ви хочете усунути освітлення SIM-картки і використовувати тільки світло Сонця/Місяця."/>
				<check_box name="Render Attached Lights" label="Включити прикріплені вогні (Face Lights)"
				 tool_tip="Це дозволить увімкнути будь-які вогні, такі як підсвічування аватара. Корисно для відключення ліхтарів при необхідності."/>
			</panel>

			<panel name="P_Shadows">
				<text name="T_Shadow_Types"
				 tool_tip="Цей параметр впливає тільки на тіні, які візуалізуються з джерел світла, інакше світло буде працювати нормально. Точкове світло (вогні, в яких відсутня функція проектування) завжди буде створювати відчуття тіней, але вони не будуть наносити їх на будь-яку поверхню Важливо, що незалежно від налаштування, яке ви вибираєте тут, текстури, спроектовані з проекційних вогнів, будуть як і раніше включені.">
					Типи тіней
				</text>
				<combo_box name="ShadowDetail">
					<combo_box.item name="0" label="Нічого"/>
					<combo_box.item name="1" label="Сонце/місяць"/>
					<combo_box.item name="2" label="Сонце/місяць + прожектори"/>
				</combo_box>
			</panel>

			<panel name="P_Shadow_Res">
				<text name="T_Shadow_Res" tool_tip="Якість тіней: це ДУЖЕ важливе налаштування. Визначає якість тіней. Також дуже навантажує комп'ютер. Це хороша ідея залишити це налаштування максимально можливим, якщо ви не фотографуєте. Коли ви фотографуєте, встановіть його в 1.0 при підготовці знімка Коли ви будете готові зробити знімок, повільно підніміть повзунок вправо. Ви повинні бути обережні з вашою частотою кадрів, поки ви піднімаєте цю настройку. робите це протягом перших кількох разів, щоб ви могли бути знайомі з рівнем тіней, який найкраще працює з вашою системою. ПРИМІТКА.">
					Якість
				</text>
				<button name="Reset_Shadow_Res" label="С" tool_tip="Скидання значення за промовчанням."/>
				<!-- Компонент RenderShadowSplitExponent Y -->
				<text name="T_Shd_Clarity" tool_tip="ЦЕ ДУЖЕ важливе налаштування. Це суттєво визначає, наскільки прозорі тіні Сонця/Місяця в цілому. Прозорість, поки не досягнутий найрізкіший результат. Зверніть увагу: ясність тіней безпосередньо пов'язана з положенням камери і Сонцем/Місяцем. Кожного разу, коли ви переміщаєте камеру або Сонце/Місяць, найкраще налаштувати це значення знову. Крім того, щоб полегшити налаштування цього значення, корисно спочатку встановити «Прозорість» до 0.0.">
					Прозорий.
				</text>
				<button name="Shd_Clarity_Reset" label="C" tool_tip="Скидання значення за промовчанням."/>
				<text name="T_Blur_Size" tool_tip="Чим вище число, тим м'якше краї тіні. Встановіть 0 для найчіткіших тіней. Цей параметр безпосередньо пов'язаний з тим, що знаходиться під ним. Це дозволяє вам встановити загальну можливу величину розмиття тіні. Якщо встановлено значення 4.00, ви можете використовувати «М'якість» тіней для настроювання розмиття тіні незалежно від оклюзії навколишнього простору.">
					Розмитість
				</text>
				<button name="Blur_Reset" label="C" tool_tip="Скидання значення за промовчанням."/>
				<!-- Компонент RenderShadowGaussian X -->
				<text name="T_Shd_Soften" tool_tip="Керує пом'якшуючим ефектом тіней Сонця/Місяця. Один простий спосіб встановити це значення для ваших конкретних потреб - спочатку встановити «Розмитість» вище приблизно до 3.0. Потім слайдер повинен пом'якшити АТ на свій смак. Зверніть увагу , що значення 0.0 ефективно відключить всі тіні Сонця/Місяця. Крім того, це не впливає на тіні, викликані проекторними вогнями">
					М'якість
				</text>
				<button name="Shd_Soften_Reset" label="C" tool_tip="Скидання значення за замовчуванням."/>
				<text name="T_Blur_Dist" tool_tip="Визначає точку, в якій тіні почнуть розмиватися щодо камери. Чим нижче значення, тим ближче буде точка розмиття тіні. УВАГА: для цього параметра необхідно активувати «Оклюзія Оточення»." >
					Відстань
				</text>
				<button name="Blur_Dist_Reset" label="C" tool_tip="Скидання значення за замовчуванням."/>
				<text name="T_FOV_Cutoff" tool_tip="Визначає відсічення FOV, при якому відображення перемикається між орто, а не на перспективну проекцію. Якщо ви отримуєте тіні, які є «стрибають», спробуйте відрегулювати це налаштування для покращення. Також коригування значень XYZ для налаштування налагодження RenderShadowSplitExponent може бути дуже корисним.">
					Розділ
				</text>
				<button name="FOV_Cutoff_Reset" label="C" tool_tip="Скидання значення за замовчуванням."/>
				<text name="T_Shd_Bias">
					Зміщення
				</text>
				<button name="Shd_Bias_Reset" label="C" tool_tip="Скидання значення за замовчуванням."/>
			</panel>

			<panel name="P_Ambient_Occlusion">
				<text name="T_Ambient_Occlusion">
					Налаштування Оклюзія Оточення
				</text>
			</panel>

			<panel name="P_Amb_Occ_Settings">
				<check_box name="UseSSAO" label="Оклюзія Оточення (глибина сприйняття)" tool_tip="Оклюзія Оточення додає затінення до всіх об'єктів. Це найбільш ефективно, коли використовуються налаштування «Ефект» та «Пом'якшення» нижче. Це може додати до знімків високий Це дуже актуально, якщо знімки зроблені з роздільною здатністю 2048 пікселів або вище."/>
			</panel>

			<panel name="P_Scale">
				<text name="T_Scale" tool_tip="Контролює область вибірки; більші області більш точні. Може бути корисно встановити ці значення високо, а потім додати трохи розмиття тіні, щоб пом'якшити їх ефект.">
					Масштаб
				</text>
				<button name="Reset_Scale" label="C" tool_tip="Скидання значення за промовчанням."/>
				<text name="T_Max_Scale" tool_tip="Керує максимальним радіусом екрана, з якого проводиться вибірка, щоб уникнути промахів у кешах графічних карт і пов'язаного з ними великого навантаження на продуктивність. Може бути корисно встановити ці значення високо, а потім додати трохи розмиття тіні , щоб пом'якшити їхній ефект.">
					Максимум
				</text>
				<button name="Reset_Max_Scale" label="C" tool_tip="Скидання значення за замовчуванням."/>
				<text name="T_Scaling_Factor" tool_tip="Масштабуючий коефіцієнт для ефекту (більш темний). Може бути корисно встановити ці значення високо, а потім додати трохи розмиття тіні, щоб пом'якшити їх ефект.">
					Коеф.
				</text>
				<button name="Reset_Scaling_Factor" label="C" tool_tip="Скидання значення за замовчуванням."/>
				<!-- Компонент RenderSSAOEffect X -->
				<text name="T_Effect" tool_tip="Керує загальним ефектом затемнення Оклюзії Оточення. Значення за умовчанням 0,8 дає майже непомітний ефект. Значення 0.0 і нижче забезпечують більш реалістичний результат. Зверніть увагу, що Оклюзія Оточення справляє шумний ефект. Крім того, стандартний аватар сітки може виглядати менш привабливим з високими значеннями ефекту через низьку якість геометрії аватара Зверніть увагу: найменше значення, яке ви можете встановити в повзунці, дорівнює 0, а в лічильнику ви можете ввести негативні значення до -10000.">
					Ефект
				</text>
				<button name="Reset_Effect" label="C" tool_tip="Скидання значення за замовчуванням."/>
				<!-- Компонент RenderShadowGaussian Y -->
				<text name="T_AO_Soften" tool_tip="Керує пом'якшенням ефекту Оклюзія Оточення. Один простий спосіб встановити це значення для ваших конкретних потреб - спочатку встановити «Розмитість» тіней вище приблизно 4.0. що значення 0.0 ефективно відключить рендеринг об'єктів оточення.">
					Пом'якшення
				</text>
				<button name="Reset_AO_Soften" label="C" tool_tip="Скидання значення за замовчуванням."/>
			</panel>
		</panel>

		<panel name="P_DoF_Glow" label="Різ./Свічок">
			<panel name="PT_DoF_Glow">
				<text name="T_DoF">
					Налаштування Глибини Різкості
				</text>
			</panel>

			<panel name="P_DoF_Settings">
				<check_box name="UseDepthofField" label="Увімкнути Глибину Різкості (DoF)"
				tool_tip="Це включить Глибину Різкості, «яка визначить відстань між найближчими і найдальшими об'єктами в сцені, які виглядають прийнятно різкими в зображенні» (Вікіпедія). Якщо ви не використовуєте його, відключіть його, і це прискорить частоту кадрів. Якщо ви не можете увімкнути цю функцію або не бачити її ефекту, увімкніть «Розширена модель освітлення» на вкладці «Світло»." />
				<check_box name="UseDoFUnderwater" label="Увімкнути Глибину Різкості під водою"
				tool_tip="Як правило, глибина різкості відключається під водою, навіть із зазначеним вище прапорцем. Цей параметр усуне це обмеження. Зверніть увагу, що вам, можливо, доведеться вручну переорієнтувати камеру на потрібні об'єкти, натиснувши на них, коли ви знаходитесь під водою. " />
				<check_box label="Фокус ГР слідує за вказівником" name="FSFocusPointFollowsPointer"
				tool_tip="Фокус глибини різкості (DoF) слідуватиме за курсором миші, ця поведінка відповідає тому, що спостерігається при використанні літаючої камери. Використовуйте разом із блокуванням фокусу Глибини різкості"/>
				<check_box name="MIC_Show_FOV" label="Показати Кут огляду (FOV) на екрані"
				tool_tip="Це покаже вам Кут Огляду камери. Усередині в'ювера можна змінити довжину об'єктива так само, як у реальному житті. Чим менше значення Кут Огляду, тим довше об'єктив камери. 50-мм об'єктив має Кут Огляду 27,0 градусів. Огляду використовуйте панель «Зум» нижче: Див.'http://en.wikipedia.org/wiki/Angle_of_view' для таблиці, що показує взаємозв'язок між Кут Огляду та фокусною відстанню об'єктива (мм). !"/>
			</panel>

			<panel name="P_Zoom">
				<text name="T_Zoom" width="85"
				 tool_tip="У реальних умовах це функція масштабування. Це змінить поле зору у вікні перегляду. Це те ж саме, що натискання Ctrl+0 або Ctrl+8. ПРИМІТКА. Це не буде працювати, якщо ви увімкнули flycam (3D SpaceNavigator)." >
					Збільшити
				</text>
				<slider_bar name="SB_Zoom" width="122"/>
				<button name="Reset_Zoom" label="С" tool_tip="Скидання значення за промовчанням."/>
				<text name="T_FOV" width="85"
				 tool_tip="Кут Огляду: це вказує який Кут Огляду ви хотіли б імітувати для ефекту Глибина Різкості. Найкраще встановити це на поточний Кут Огляду.">
					Кут огляду
				</text>
				<slider_bar name="SB_FOV" width="122"/>
				<button name="Reset_FOV" label="C" tool_tip="Скидання значення за замовчуванням."/>
				<text name="T_F_Number" tool_tip="У реальних умовах це налаштування діафрагми для об'єктива, і чим нижче значення, тим коротшою буде глибина поля. Те ж саме стосується SL.">
					Діафрагма
				</text>
				<button name="Reset_F_Number" label="C" tool_tip="Скидання значення за замовчуванням."/>
				<text name="T_Focal_Length" tool_tip="Фокусна відстань (мм): Це вказує на те, що Фокусна відстань/Довжина об'єктива імітує ефект Глибини Різкості. Вищі числа дають більш вузьку глибину різкості.">
					Фок.
				</text>
				<button name="Reset_Focal_Length" label="C" tool_tip="Скидання значення за замовчуванням."/>
				<text name="T_Foc_Time" tool_tip="Час фокусування: встановлює час у секундах, який потрібно змінити фокус з одного об'єкта.">
					Час Фок.
				</text>
				<button name="Reset_Foc_Time" label="C" tool_tip="Скидання значення за замовчуванням."/>
				<text name="T_CoC" tool_tip="Коло Розмиття: це ДУЖЕ ВАЖЛИВА ВСТАНОВКА. Він визначає силу самого розмиття. Він не змінює глибину різкості, він регулює, наскільки ці об'єкти за межами цього будуть розмитими. Також ви можете отримати доступ до негативних значень. для цікавих ефектів у текстовому полі.">
					Розмиття
				</text>
				<button name="Reset_CoC" label="C" tool_tip="Скидання значення за замовчуванням."/>
				<text name="T_Resolution" tool_tip="Дозвіл: Це визначає якість ефекту Глибини Різкості. Для не-фотографії використовуються «.25». Для створення знімків «.50» або «.70» дуже приємно. Для якісної зйомки найкраще 1.00 Високі значення уповільнять ваш FPS! Також ви можете отримати доступ до негативних значень для цікавих ефектів у текстовому полі.">
					Дозвіл
				</text>
				<button name="Reset_Resolution" label="C" tool_tip="Скидання значення за замовчуванням."/>
			</panel>

			<panel name="P_Glow_Settings">
				<text name="T_Glow_Settings">
					Налаштування Свічення
				</text>
			</panel>

			<panel name="P_Glow_Quality">
				<text name="T_Glow_Quality" tool_tip="Це визначить якість ефекту свічення, чим вище тим краще. Мало візуальної різниці між 8 і 10.">
					якість
				</text>
				<button name="Reset_Glow_Quality" label="C" tool_tip="Скидання значення за замовчуванням."/>
			</panel>

			<panel name="P_Glow_Iterations">
				<text name="T_Glow_Iterations" tool_tip="Кількість повторів світіння (вище = ширше і плавніше і трохи повільніше).">
					Повтори
				</text>
				<button name="Reset_Glow_Iterations" label="C" tool_tip="Скидання значення за замовчуванням."/>
				<text name="T_Glow_Strength" tool_tip="Адитивна сила свічення. Для цього ефекту потрібні дуже низькі значення. Почніть з малого!">
					Сила
				</text>
				<button name="Reset_Glow_Strength" label="C" tool_tip="Скидання значення за замовчуванням."/>
				<text name="T_Luminance" tool_tip="Мінімальна інтенсивність яскравості, необхідна для того, щоб розглянути об'єкт, досить яскравий, щоб автоматично світитися.">
					Яскравість
				</text>
				<button name="Reset_Luminance" label="C" tool_tip="Скидання значення за замовчуванням."/>
				<text name="T_Warmth" tool_tip="Кількість виділення тепла для використання (порівняно з яскравістю). 0 = світло, 1.0 = тепло. У ДУЖЕ МАЛОГО НЕМАЄ ЕФЕКТУ!">
					Теплота
				</text>
				<button name="Reset_Warmth" label="C" tool_tip="Скидання значення за замовчуванням."/>
				<text name="T_Glow_Width" tool_tip="Розмір зразка світіння. Вище = більш широке і м'яке свічення, але в результаті воно стане більш піксельним.">
					Широта
				</text>
				<button name="Reset_Glow_Width" label="C" tool_tip="Скидання значення за замовчуванням."/>
				<text name="T_Alpha" tool_tip="В принципі, наскільки яскравим може бути свічення.">
					Альфа
				</text>
				<button name="Reset_Alpha" label="C" tool_tip="Скидання значення за замовчуванням."/>
			</panel>
		</panel>

		<panel name="P_General" label="Загальні.">
			<panel name="PT_General">
				<text name="T_General">
					Загальні налаштування відображення
				</text>
			</panel>

			<panel name="P_General_Settings">
				<text name="T_Draw_Distance" tool_tip="Це встановлює найбільшу відстань малювання. Високі значення уповільнять ваш FPS!">
					Малювання
				</text>
				<button name="Reset_Draw_Distance" label="C" tool_tip="Скидання значення за замовчуванням."/>
				<text name="T_Avi_Count" tool_tip="Максимальна кількість інших аватарів для малювання в сцені. Дуже корисна для ситуацій, коли безліч аватарів уповільнюють ваш FPS.">
					Полковник Ават.
				</text>
				<button name="Reset_Avi_Count" label="C" tool_tip="Скидання значення за замовчуванням."/>
				<text name="T_Avi_Detail" tool_tip="Встановлює якість відтворення аватарів. Чим вище, тим краще!">
					Кач. Ават.
				</text>
				<button name="Reset_Avi_Detail" label="C" tool_tip="Скидання значення за замовчуванням."/>
				<text name="T_Avi_Physics" tool_tip="Керує рівнем деталізації фізики аватара (наприклад, фізика грудей). Чим вище, тим краще.">
					Фіз.
				</text>
				<button name="Reset_Avi_Physics" label="C" tool_tip="Скидання значення за замовчуванням."/>
				<text name="T_Particle_Cnt" tool_tip="Встановлює максимальну кількість частинок для малювання.">
					Частинки
				</text>
				<button name="Reset_Particle_Cnt" label="C" tool_tip="Скидання значення за замовчуванням."/>
				<text name="T_Terrain_Scale" tool_tip="Встановлює якість текстури землі за умовчанням (ландшафт).">
					Земля
				</text>
				<button name="Reset_Terrain_Scale" label="C" tool_tip="Скидання значення за замовчуванням."/>
				<text name="T_Terrain_Quality" tool_tip="Встановлює якість місцевості. Високі цифри означають більш докладний ландшафт на відстані.">
					Місцевість
				</text>
				<button name="Reset_Terrain_Quality" label="С" tool_tip="Скидання значення за промовчанням."/>
				<text name="T_Object_Detail" tool_tip="Елемент керування, коли об'єкти меншої деталізації можуть використовуватися для зменшення вартості рендерингу. Вищі значення викликають запізнення, використання з обережністю." >
					Об'єкти
				</text>
				<button name="Reset_Object_Detail" label="C" tool_tip="Скидання значення за замовчуванням."/>
				<text name="T_Flexi_Detail" tool_tip="Керує рівнем деталізації гнучких об'єктів. Вища означає більш високу деталізацію.">
					Гнучкі
				</text>
				<button name="Reset_Flexi_Detail" label="C" tool_tip="Скидання значення за замовчуванням."/>
				<text name="T_Tree_Detail" tool_tip="Контролює рівень деталізації рослинності. Вищі цифри дають високу деталізацію.">
					Дерева
				</text>
				<button name="Reset_Tree_Detail" label="C" tool_tip="Скидання значення за замовчуванням."/>
				<text name="T_Sky_Detail" tool_tip="Керує деталізацією неба WindLight. Нижчі цифри дають кращу продуктивність і менше, ніж прекрасне небо.">
					Небо
				</text>
				<button name="Reset_Sky_Detail" label="C" tool_tip="Скидання значення за замовчуванням."/>
			</panel>

			<panel name="P_Vignetting">
				<text name="T_VignetteX" tool_tip="Віньєтка - це затемнення кутів фотографії по краю.">
					Віньєтка
				</text>
				<button name="Reset_VignetteX" label="С" tool_tip="Скидання значення за промовчанням."/>
				<text name="T_VignetteY" tool_tip="Впливає на чорноту затемнення по краю.">
					Контраст
				</text>
				<button name="Reset_VignetteY" label="C" tool_tip="Скидання значення за замовчуванням."/>
				<text name="T_VignetteZ" tool_tip="Впливає на розмір затіненої області.">
					Розмір
				</text>
				<button name="Reset_VignetteZ" label="C" tool_tip="Скидання значення за замовчуванням."/>
			</panel>

			<panel name="P_Render">
				<check_box label="Включити Дистанцію Малювання" name="UseFarClip" tool_tip="Включає Дистанцію Малювання, якщо ви вимкнете цю функцію, буде використовуватися попередні налаштування Дистанції Малювання."/>
				<check_box label="Динамічний рівень деталізації" name="RednerLod1" tool_tip="Це включає функцію, яка дозволяє динамічно регулювати рівень деталізації у сцені, коли ви рухаєтеся далі від об'єктів. Це допомагає підвищити продуктивність, а також може знизити якість об'єктів у сцені ."/>
				<check_box label="Відтворювати лише видимі об'єкти" tool_tip="Це дозволяє обробляти/малювати лише ті об'єкти, які знаходяться в полі зору камери, а не ховатися за будь-чим іншим. Зазвичай це підсилювач продуктивності. Іноді це може фактично знизити продуктивність, особливо коли у сцени/сима є кілька об'єктів. Перейдіть, щоб дізнатися, допомагає це чи ні!" name="UssOcclusion1"/>
				<check_box label="Анізотропна фільтрація (текстури)" tool_tip="Це дозволяє підвищити чіткість текстур." name="Anisotropic"/>
				<check_box label="Відображати частинки прикріплених до аватарів" tool_tip="Дозволяє відображати всі будь-які частинки, прикріплені до інших аватарів." name="Render Attached Particle"/>
			</panel>

			<panel name="P_Anti-aliasing">
				<text name="T_Anti-aliasing" tool_tip="Визначає, наскільки точні та чіткі краї об'єктів. На графічних картах верхнього рівня вищі значення практично не впливають на продуктивність. На нижчих відеокартах вищі значення можуть уповільнювати роботу.">
					Згладжування
				</text>
				<combo_box name="fsaa" label="Згладжування">
					<combo_box.item label="Вимкнено (Грубі краї)" name="FSAADisabled"/>
					<combo_box.item label="2x (Гладкі краї)" name="2x"/>
					<combo_box.item label="4x (Гладкі краї)" name="4x"/>
					<combo_box.item label="8x (Ще більш гладкі краї)" name="8x"/>
					<combo_box.item label="16x (Дуже гладкі краї)" name="16x"/>
				</combo_box>

				<text name="T_Texture_Bumpiness" tool_tip="Керує силою та дозволом нормалей та рельєфних карток.">
					Рельєф Текстур
				</text>
				<combo_box name="BumpStrengthSelection">
					<combo_box.item label="Дуже тонкий (дуже слабкий)" name="0"/>
					<combo_box.item label="Тонший (слабший)" name="1"/>
					<combo_box.item label="Добре (слабкий)" name="2"/>
					<combo_box.item label="Нормальний" name="3"/>
					<combo_box.item label="Грубий (сильний)" name="4"/>
					<combo_box.item label="Більш грубий (дуже сильний)" name="5"/>
				</combo_box>
			</panel>
		</panel>

		<panel name="P_Aids" label="Доп.">
			<panel name="PT_Aids">
				<text name="T_Aids">
					Допоміжні засоби
				</text>
			</panel>

			<check_box label="Показати Bounding Boxes для всіх вогнів" name="Lights"/>
			<check_box label="Показати радіус світла для обраного" name="Show Light Radius for Selection"/>
			<check_box label="Показати Bounding Boxes для Об'єктів" name="Bounding Boxes"/>
			<check_box label="Показати Статистику" name="Statistics Bar"/>
			<check_box label="Показати Консоль камери" name="Camera"/>
			<check_box label="Показати Консоль Текстур" name="Texture Console"/>
			<check_box label="Показати RGB-I Колір під курсором" name="Show Color Under Cursor"/>
			<check_box label="Підсвітити прозорі об'єкти" name="Highlight Transparent"/>
			<check_box label="Показати сцену Каркасом" name="Wireframe"/>
			<check_box label="Показати HUD на Вашому Аватарі" name="Show HUD Attachments"/>
			<check_box label="Повільна анімація Ваш Аватар (для вас)" name="Slow Motion Animations"/>
			<button name="Rebake Texture" label="Примусово оновити зовнішність (Rebake)" />
			<button name="Set Window Size..." label="Встановити розмір вікна..." />
			<button name="Debug Settings" label="Показати Меню Налаштувань налагодження" />

			<panel name="P_Quick_Stats">
				<text name="T_Quick_Stats" tool_tip="Тут ви можете знайти дуже корисну статистику для оцінки продуктивності системи. Розгорніть/ Згорніть елементи нижче, клацнувши їх ярлики.">
					Швидка Статистика
				</text>
			</panel>

			<scroll_container name="statistics_scroll">
				<container_view name="statistics_view">
					<stat_view name="basic">
						<stat_bar name="fps" label="Кадрів в секунду" tool_tip="FPS: скільки разів на секунду ваш комп'ютер перемальовує (або оновлює) те, що знаходиться на екрані. Більші числа краще. Частота кадрів від 12 до 15 є загальною для анімацій, 24 - стандартом для зображень, що рухаються, а 25(PAL)/30(NTSC) кадрів в секунду (FPS) - це швидкість для широкомовного телебачення."/>
						<stat_bar name="bandwidth" label="Пропускна спроможність" tool_tip="Пропускна спроможність: Скільки даних передається між вашим комп'ютером і віртуальним світом. Це число сильно варіюється в залежності від того, які налаштування смуги пропускання ви використовували, де ви знаходитесь в світі , що відбувається, і чи завантажуєте ви деякі речі (об'єкти/текстури/і т.д.), які знаходяться у вашій області зору Якщо пропускна спроможність становить 0 Кбіт/с, щось може бути неправильним (ви можете бути частково відключені )."/>
						<stat_bar name="ktrisframe" label="Ктріс малювання за кадр" tool_tip="Ктріс малювання: (за кадр) Створені комп'ютером 3D-об'єкти побудовані з трикутників (основна геометрична форма). Це підрахунок числа трикутників або «трис» у кадрі поточної сцени."/>
						<stat_bar name="ktrissec" label="Ктріс малювання за сік." tool_tip="КТрис малюнок: (в секунду) Створені комп'ютером 3D-об'єкти побудовані з трикутників (основна геометрична форма). Це підрахунок числа трикутників або «трис» в секунду."/>
						<stat_bar name="objs" label="Усього Об'єктів" tool_tip="Усього Об'єктів: Кількість об'єктів, які в даний час відображаються, в тому числі: Прими, Аватари, Ландшафти, Дерева, Групи частинок і Частини води."/>
						<stat_bar name="newobjs" label="Нові Об'єкти" tool_tip="Нові Об'єкти: Кількість об'єктів, що завантажуються в секунду."/>
						<stat_bar name="numimagesstat" label="Підрахунок текстур" tool_tip="Підрахунок: кількість завантажених унікальних текстур."/>
					</stat_view>
				</container_view>
			</scroll_container>
		</panel>

		<panel name="P_Cam" label="Cam.">
			<panel name="PT_Cam">
				<text name="T_Cam">
					Налаштування 3D-миші (джойстик)
				</text>
			</panel>

			<panel name="P_Cam_Settings">
				<text name="T_LR_Axis" tool_tip="Регулює чутливість руху вліво/вправо. Якщо вам важко рухатися з точністю, використовуйте нижчі значення шкали." width="100">
					Ліворуч/праворуч
				</text>
				<slider_bar name="SB_LR_Axis" width="110"/>
				<button name="Reset_LR_Axis" label="C" tool_tip="Скидання значення за замовчуванням."/>
				<text name="T_UD_Axis" tool_tip="Регулює чутливість руху Вгору/Вниз. Якщо вам важко рухатися з точністю, використовуйте нижчі значення шкали." width="100">
					Вверх вниз
				</text>
				<slider_bar name="SB_UD_Axis" width="110"/>
				<button name="Reset_UD_Axis" label="C" tool_tip="Скидання значення за замовчуванням."/>
				<text name="T_IO_Axis" tool_tip="Регулює чутливість руху Вперед/Назад. Якщо вам важко рухатися з точністю, використовуйте нижчі значення шкали." width="100">
					Вперед назад
				</text>
				<slider_bar name="SB_IO_Axis" width="110"/>
				<button name="Reset_IO_Axis" label="C" tool_tip="Скидання значення за замовчуванням."/>
				<text name="T_Tilt" tool_tip="Регулює чутливість Висота. Якщо вам важко рухатися з точністю, використовуйте нижчі значення шкали." width="100">
					Висота
				</text>
				<slider_bar name="SB_Tilt" width="110"/>
				<button name="Reset_Tilt" label="C" tool_tip="Скидання значення за замовчуванням."/>
				<text name="T_Spin" tool_tip="Регулює чутливість Ризикання. Якщо вам важко рухатися з точністю, використовуйте нижчі значення шкали." width="100">
					Ризикання
				</text>
				<slider_bar name="SB_Spin" width="110"/>
				<button name="Reset_Spin" label="C" tool_tip="Скидання значення за замовчуванням."/>
				<text name="T_Roll" tool_tip="Регулює чутливість Крена. Якщо вам важко рухатися з точністю, використовуйте нижчі значення шкали." width="100">
					Крен
				</text>
				<slider_bar name="SB_Roll" width="110"/>
				<button name="Reset_Roll" label="C" tool_tip="Скидання значення за замовчуванням."/>
				<text name="T_Zoom_Speed" tool_tip="Регулює чутливість швидкості масштабування. Якщо вам важко масштабувати з точністю, використовуйте нижчі значення шкали." width="100">
					Швидкість Зуму
				</text>
				<slider_bar name="SB_Zoom_Speed" width="110"/>
				<button name="Reset_Zoom_Speed" label="C" tool_tip="Скидання значення за замовчуванням."/>
				<text name="T_Feathering" tool_tip="Установка повзунка повністю вправо зробить камеру дуже рухомою, забезпечуючи повний контроль джойстиком. Установка повзунка повністю вліво зробить камеру дуже інертною, ніби камера важка; добре для знімків, не підходить для відео." width="100">
					Легкість
				</text>
				<slider_bar name="SB_Feathering" width="110"/>
				<button name="Reset_Feathering" label="C" tool_tip="Скидання значення за замовчуванням."/>
			</panel>

			<panel name="P_Axis_Mapping">
				<spinner label="Встановлення осі масштабування" name="JoystickAxis6"
				 tool_tip="Керує, на яку вісь миші відображається функція масштабування (для роботи з нею)."/>
				<check_box label="Увімкнути 3Д Мишу" tool_tip="Це включає 3Д Мишу." name="enable_joystick"/>
				<check_box name="CB_ZoomDirect" label="Керування масштабом (див. Підказку!)"
				 tool_tip="Щоб управління масштабуванням працювало, ви повинні встановити 'Установка осі масштабування' вище '4'."/>
				<check_box name="CB_AutoLeveling" label="Автовирівнювання (запобігає нахилу)"
				 tool_tip="При включенні камера завжди залишається на рівні."/>
				<check_box name="CB_Move_Avatar" label="Двигати аватар 3Д-мишкою"
				 tool_tip="Коли увімкнено, 3Д-миша перемістить ваш аватар."/>
				<check_box name="CB_Move_Objects" label="Двигати об'єкти 3Д-мишкою (будувати)"
				 tool_tip="Використовує 3D-мишу для переміщення об'єктів під час створення та редагування."/>
				<check_box label="Показати Кут огляду (FOV) на екрані"
				 tool_tip="Це покаже вам Кут Огляду камери. Усередині в'ювера можна змінити довжину об'єктива так само, як у реальному житті. Чим менше значення Кута Огляду, тим довше об'єктив камери. 50-мм об'єктив має Кут Огляду 27.0 градусів. Для налаштування Кута Огляду використовуйте панель «Зум» нижче: Див.'http://en.wikipedia.org/wiki/Angle_of_view' в таблицю, що показує взаємозв'язок між кутом огляду і фокусною відстанню об'єктива (мм)."
				 name="CAM_Show_FOV"/>
				<check_box label="Показати деталізацію камери в консолі" name="Camera"/>
			</panel>

			<panel name="P_Viewer_Cam_Menu">
				<text name="PT_Viewer_Cam_Menu">
					Меню налаштування Камери
				</text>
			</panel>

			<panel name="P_Viewer_Cam_Menu_Settings">
				<tab_container name="TC_Viewer_Cam_Menu_Settings">
					<panel name="CamMov" label="Рух Камери">
						<panel name="P_Cam2">
							<text name="T_Zoom2" tool_tip="У реальних умовах це функція масштабування. Це змінить кут огляду у вікні перегляду. Це те саме, що натискання Ctrl+0 або Ctrl+8. ПРИМІТКА. Це не буде працювати, якщо ви ввімкнули flycam (3D SpaceNavigator).">
								Кут огляду
							</text>
							<button name="Reset_Zoom2" label="C" tool_tip="Скидання значення за замовчуванням."/>
							<text name="T_Zoom_Speed2" tool_tip="Контролює, як швидко та повільно камера буде збільшувати та зменшувати. Вищі значення забезпечують повільніше та плавніше масштабування.">
								Швидкість
							</text>
							<button name="Reset_Zoom_Speed2" label="С" tool_tip="Скидання значення за промовчанням."/>
							<text name="T_Camera_Lag" tool_tip="На скільки камера відстає від руху аватара (0 = ні, 30 = швидкість аватара).">
								Відставання
							</text>
							<button name="Reset_Camera_Lag" label="C" tool_tip="Скидання значення за замовчуванням."/>
							<text name="T_Camera_Offset" tool_tip="Керує тим, наскільки камера зміщена/віддалена від точки зору за промовчанням.">
								Зміщення
							</text>
							<button name="Reset_Camera_Offset" label="C" tool_tip="Скидання значення за замовчуванням."/>
							<text name="T_Cam_Smoothing" tool_tip="Контролює, як гладко камера розганяється і зупиняється. Вищі значення дають більш плавний (і трохи повільніший) рух.">
								Згладжування
							</text>
							<button name="Reset_Cam_Smoothing" label="C" tool_tip="Скидання значення за замовчуванням."/>
						</panel>
					</panel>

					<panel name="P_Mouse" label="Миша">
						<panel name="P_Mouse_Settings">
							<text name="T_Mouse_Sens" tool_tip="Контролює чуйність миші в режимі Mouselook.">
								Чутливість
							</text>
							<button name="Reset_Mouse_Sens" label="C" tool_tip="Скидання значення за замовчуванням."/>
							<check_box label="Показати аватар у режимі Mouselook" tool_tip="Відображає аватар і вкладення нижче шиї, в режимі Mouselook. Значення за замовчуванням: Вимк." name="first_person_avatar_visible"/>
							<check_box label="Згладжувати рухи в Mouselook" tool_tip="Згладжує рух миші в режимі Mouselook." name="MouseSmooth"/>
						</panel>
					</panel>

					<panel name="P_Misc" label="Різне">
						<panel name="P_Misc_Settings">
							<check_box label="Клік на аватар тримає положення камери" name="clickonavatarkeepscamera"
							 tool_tip="Зазвичай натискання на аватар скидає положення камери. Цей параметр усуває цю поведінку."/>
							<check_box label="Скинути позицію камери після телепорту" name="FSResetCameraOnTP"
							 tool_tip="Зазвичай положення камери скидається при телепортації (в межах регіону). Цей параметр запобігає цій поведінці."/>
							<check_box label="Вимкнути мінімальну відстань камери" name="disableminzoomdist"
							 tool_tip="Вимикає обмеження на найближчій відстані від камери до об'єкта."/>
							<check_box name="ignorecameraconstraints" label="Дозволити рухати камеру без перешкод"
							 tool_tip="Ігнорує «виштовхування» камери з об'єктів. ВИМАГАЄ ПЕРЕЗАПУСК!"/>
							<check_box name="resetcamerapositiononmovement" label="Скинути позицію камери під час руху"
							 tool_tip="Скидає камеру в положення за умовчанням під час переміщення аватара"/>
						</panel>
					</panel>
				</tab_container>
			</panel>
		</panel>
	</tab_container>
</floater>



