<?xml version="1.0" encoding="utf-8" standalone="yes" ?>
<floater
	positioning="centered"
	legacy_header_height="18"
	can_resize="true"
	can_dock="false"
	can_close="true"
	height="396"
	min_height="364"
	min_width="200"
	layout="topleft"
	name="animation_overrider"
	help_topic="animation_overrider"
	save_rect="true"
	save_visibility="true"
	single_instance="true"
	save_dock_state="false"
	title="Animation Overrider"
	width="200">

	<floater.string
		name="ao_no_sets_loaded">
No Sets Loaded
	</floater.string>

	<floater.string
		name="ao_no_animations_loaded">
No Animations Loaded
	</floater.string>
	<floater.string
		name="ao_dnd_only_on_full_interface">
You can only drag and drop an animation notecard on the full interface window. Click on the wrench icon to open it.
	</floater.string>

	<floater.string
		name="ao_add_blank_label">
New empty set...
	</floater.string>
	<floater.string
		name="ao_add_clone_label">
Clone current set...
	</floater.string>

	<floater.string
		name="ao_track_main">
Main
	</floater.string>
	<floater.string
		name="ao_no_track_animations">
Empty Track - drop an animation here
	</floater.string>
	<floater.string
		name="ao_group_tooltip">
Animation group - these play together:
	</floater.string>
	<floater.string
		name="ao_member_tooltip">
Animation group entry - plays together with the rest of its group. Double-click to preview it alone.
	</floater.string>
	<floater.string
		name="ao_cm_expand">
Expand
	</floater.string>
	<floater.string
		name="ao_cm_collapse">
Collapse
	</floater.string>
	<floater.string
		name="ao_cm_rename_group">
Rename group...
	</floater.string>
	<floater.string
		name="ao_cm_move_out">
Move out of group
	</floater.string>
	<floater.string
		name="ao_cm_find_original">
Find Original
	</floater.string>
	<floater.string
		name="ao_cm_delete">
Delete
	</floater.string>
	<floater.string
		name="ao_dnd_merge">
Drop to group with this animation
	</floater.string>
	<floater.string
		name="ao_dnd_add_to_group">
Drop to add to this group
	</floater.string>
	<floater.string
		name="ao_dnd_add_to_track">
Drop to add to this track
	</floater.string>
	<floater.string
		name="ao_dnd_folder_group">
Drop folder to create an animation group
	</floater.string>
	<floater.string
		name="ao_dnd_folder_pour">
Drop folder to add its animations to this track
	</floater.string>

	<panel
		name="animation_overrider_outer_panel"
		filename="panel_ao.xml"
		left="0"
		top="16"
		width="200"
		height="378"
		follows="all"
		layout="topleft">
	</panel>
</floater>
