<?xml version="1.0" encoding="utf-8" standalone="yes"?>
<!--alba-->
<floater name="Inventory" title="INVENTAIRE">
	<floater.string name="Title">
		INVENTAIRE
	</floater.string>
	<floater.string name="TitleFetching">
		INVENTAIRE (récupération de [ITEM_COUNT] articles en cours) [FILTER]
	</floater.string>
	<floater.string name="TitleCompleted">
		INVENTAIRE ([ITEM_COUNT] articles) [FILTER]
	</floater.string>
	<floater.string name="Fetched">
		Récupéré
	</floater.string>
	<panel label="Panneau Inventaire" name="Inventory Panel"/>
</floater>
