<?xml version="1.0" encoding="utf-8" standalone="yes" ?>
<floater name="floater_avatar_render_settings" title="Wyjątki renderowania awatarów">
	<string name="av_never_render" value="Nigdy"/>
	<string name="av_always_render" value="Zawsze"/>
	<name_list name="render_settings_list">
		<name_list.columns label="Imię" name="name" />
		<name_list.columns label="Pełne detale" name="setting" />
	</name_list>
	<panel name="add_subpanel">
		<menu_button label="Dodaj kogoś..." name="plus_btn" tool_tip="Działania na wybranej osobie" />
	</panel>
</floater>
