<?xml version="1.0" encoding="utf-8" standalone="yes"?>
<panel label="Komunikacja" name="im">
	<string name="AutoresponseItemNotSet">
		Brak ustawionego
	</string>
	<string name="AutoresponseItemNotAvailable">
		Niedostępny
	</string>
	<string name="AutoresponseItemNotLoggedIn">
		Zaloguj się
	</string>
	<tab_container label="Prywatność" name="tabs">
		<panel label="Ogólne" name="tab-general">
			<panel.string name="log_in_to_change">
				Zaloguj się, by zmienić
			</panel.string>
			<button label="Wyczyść historię" tool_tip="Wyczyść zapisane obrazy, ostatnią lokalizację, historię teleportów, bufor stron internetowych i bufor danych tekstur" name="clear_cache"/>
			<text name="cache_size_label">
				(miejsca, obrazy, strony web, historia wyszukiwarki)
			</text>
			<check_box label="Pokaż mój profil w wynikach wyszukiwarki" name="online_searchresults"/>
			<check_box label="Mój status online dostępny tylko dla znajomych i grup" name="online_visibility"/>
			<check_box label="Tylko znajomi i grupy mogą wysyłać do mnie wiadomości lub dzwonić głosowo" name="voice_call_friends_only_check"/>
			<check_box label="Wyłącz mikrofon po zakończeniu rozmowy głosowej" name="auto_disengage_mic_check"/>
			<check_box label="Pozwól oskryptowanym obiektom znać moje obecne ustawienie języka" name="LanguageIsPublic"/>
			<check_box label="Automatycznie akceptuj nowe przedmioty" name="Auto_Accept_New_Inventory"/>
			<check_box label="Klasyczne powiadomienia akceptacji/odrzucenia przedmiotu" name="FSUseLegacyInventoryAcceptMessages" tool_tip="Gdy włączysz tą opcję, to Przeglądarka będzie wysyłać powiadomienia o akceptacji/odrzuceniu przedmiotu tylko po naciśnięciu odpowiedniego przycisku. Gdy wyłączysz tą opcję, to powiadomienie będzie wysłane automatycznie zaraz po tym, gdy przedmiot zostanie zaakceptowany. Ta opcja nie ma żadnej mocy, gdy przedmioty są akceptowane automatycznie."/>
			<check_box label="Automatycznie pokazuj akceptowane przedmioty" name="Show_In_Inventory"/>
			<check_box label="Automatycznie pokazuj noty, tekstury i landmarki po zaakceptowaniu" name="Show_New_Inventory"/>
			<check_box label="Automatycznie pokazuj zdjęcia w Szafie po załadowaniu" name="FSOpenInventoryAfterSnapshot"/>
			<check_box label="Twórz efekty cząsteczkowe, gdy dam jakiś przedmiot innej osobie" name="FSCreateGiveInventoryParticleEffect"/>
			<check_box label="Pokaż moje ulubione landmarki przy logowaniu (w rozwijanym menu &apos;Rozpocznij w&apos;)" name="favorites_on_login_check"/>
			<button label="Lista zablokowanych / wyciszonych" name="block_list"/>
		</panel>
		<panel label="Logi rozmów" name="tab-logging">
			<text name="logging_label">
				Zapisywanie:
			</text>
			<combo_box name="conversation_log_combo" tool_tip="Dziennik: Lista konwersacji rozpoczętych przez Ciebie lub kogoś innego. Logi rozmów: Rzeczywisty tekst pokazywany na ekranie.">
				<item name="log_and_transcripts" label="Dziennik i logi rozmów"/>
				<item name="log_only" label="Tylko dziennik"/>
				<item name="no_log_or_transcript" label="Nie zapisuj dziennika ani logów rozmów"/>
			</combo_box>
			<button label="Wyczyść dziennik" name="clear_log"/>
			<button label="Usuń logi rozmów" name="delete_transcripts"/>
			<check_box name="LogNearbyChat" label="Zapisuj log czatu lokalnego" tool_tip="Zapisuj wiadomości czatu lokalnego na twardym dysku swojego komputera"/>
			<check_box label="Używaj starego formatu nazw plików dla logów rozmów" name="UseLegacyIMLogNames" tool_tip="Włączenie tej opcji spowoduje używanie starego formatu nazw plików dla logów rozmów (Nazwa Użytkownika) zamiast nowego (nazwa_użytkownika)."/>
			<check_box label="Dodawaj datę do nazw plików logów rozmów" name="LogFileNamewithDate" tool_tip="Dodawaj znaczniki czasu do logów czatów oraz IM w formacie czat-RRRR-MM-DD oraz 'Nazwa pliku IM'-RRRR-MM."/>
			<check_box label="Używaj wbudowanej przeglądarki logów" name="FSUseBuiltInHistory" tool_tip="Używaj wbudowanej przeglądarki logów do przeglądania logów czatów. Gdy wyłączysz tą opcję, to logi będą się otwierać w domyślnym edytorze tekstowym Twojego systemu operacyjnego."/>
		</panel>
		<panel label="Śledzenie spojrzeń" name="tab-lookat">
			<check_box label="Pokazuj na co patrzą inni:" name="showlookat" tool_tip="To ustawienie pozwala włączyć wizualne pokazywanie wskaźnika animacji (punktu LookAt), którego używa przeglądarka do obracania oczami, głową oraz tułowiem. Może on także być używany do określenia punktu zaczepienia kamery awatara."/>
			<text name="lookatshownames" tool_tip="Wybierz, czy przy celowniczkach mają być pokazywane imiona awatarów">
				Format imion przy celach spojrzeń
			</text>
			<combo_box name="lookatshownames_combobox">
				<combo_box.item label="Nie pokazuj" name="None"/>
				<combo_box.item label="Pełne imię" name="Complete_Name"/>
				<combo_box.item label="Wyświetlane imię" name="Display_Name"/>
				<combo_box.item label="Stare imię" name="Legacy_Name"/>
				<combo_box.item label="Nazwa konta" name="User_Name"/>
			</combo_box>
			<check_box label="Nie pokazuj celu mojego własnego spojrzenia" name="LookAtHideOwn" tool_tip="Nie pokazuj mi mojego własnego celowniczka"/>
			<check_box label="Renderuj linie do celów spojrzeń" name="ExodusLookAtLines" tool_tip="Renderuj linie od awatarów do celowniczków ich celów spojrzeń" />
			<text name="mylookat">
				Moje cele spojrzeń:
			</text>
			<check_box label="Nie pokazuj innym, gdzie patrzę" name="privatelookat" tool_tip="Zapobiega wysyłaniu na serwer informacji o własnym celu spojrzenia"/>
			<check_box label="Nie pokazuj celu mojego spojrzenia nawet na moim własnym ekranie" name="privateLocalLookat" tool_tip="Zapobiega poruszaniu głową i skupianiu wzroku Twojego awatara na Twoim własnym ekranie. Ten ruch nie musi być widoczny dla innych nawet gdy ta opcja jest wyłączona."/>
			<check_box label="Nie pokazuj innym celów moich wskazań" name="privatepointat" tool_tip="Zapobiega wysyłaniu innym celów wskazanych myszką"/>
		</panel>
		<panel label="Autoodpowiedzi 1" name="tab-autoresponse-1">
			<text name="text_box3">
				Gdy jestem zajęty/a:
			</text>
			<text name="autorespond_response_label">
				Do wszystkich awatarów, gdy włączony jest tryb autoodpowiedzi:
			</text>
			<text name="autorespond_nf_response_label">
				Do nieznajomych, gdy włączony jest tryb autoodpowiedzi dla nieznajomych:
			</text>
			<check_box label="Wysyłaj autoodpowiedź, gdy mój awatar śpi (jest w trybie 'away'):" name="send_away_av_response" tool_tip="Wysyłaj tekst poniżej, gdy ktoś wysyła Ci wiadomość IM, a Twój awatar w tym momencie akurat śpi (jest w trybie 'away')."/>
			<check_box label="Wysyłaj autoodpowiedzi do WYCISZONYCH awatarów:" name="send_muted_av_response" tool_tip="Wysyła poniższy tekst do osoby, która wysyła Ci IM, a jest przez Ciebie wyciszona."/>
		</panel>
		<panel label="Autoodpowiedzi 2" name="tab-autoresponse-2">
			<text name="autorespond_rto_response_label">
				Do wszystkich awatarów, gdy włączony jest tryb odrzucania propozycji i próśb o teleportację:
			</text>
			<check_box label="Nie odrzucaj próśb o teleportację (i nie wysyłaj autoodpowiedzi) od znajomych" name="FSDontRejectTeleportOffersFromFriends" />
			<text name="autorespond_rfr_response_label">
				Do wszystkich awatarów, gdy włączony jest tryb odrzucania zaproszeń do znajomych:
			</text>
			<text name="autoresponse_item_label" width="300">
				Przedmiot wysyłany ze wszystkimi autoodpowiedziami:
			</text>
			<fs_copytrans_inventory_drop_target name="autoresponse_item" tool_tip="Przeciągnij i upuść przedmiot z Szafy w tym miejscu."/>
			<button label="Czyść" name="clear_autoresponse_item"/>
		</panel>
	</tab_container>
</panel>
