<?xml version="1.0" encoding="utf-8" standalone="yes"?>
<panel label="モノ" name="objects panel">
  <panel name="sidepanel_inventory_panel" label="">
    <layout_stack name="inventory_layout_stack">
      <layout_panel name="main_inventory_layout_panel">
        <panel name="panel_main_inventory" label="" />
      </layout_panel>
      <layout_panel name="inbox_layout_panel">
        <panel name="marketplace_inbox" label="">
          <string name="InboxLabelWithArg">受け取ったアイテム（[NUM]個）</string>
          <string name="InboxLabelNoArg">受け取ったアイテム</string>
          <button label="Received items" name="inbox_btn" />
          <button name="reload_received_items_btn" tool_tip="受け取ったアイテムリストをリロードします。" />
          <text name="inbox_fresh_new_count">新着[NUM]個</text>
          <panel name="inbox_inventory_placeholder_panel" tool_tip="アイテムをインベントリにドラッグアンドドロップして使用します。">
            <text name="inbox_inventory_placeholder">マーケットプレイスで購入したものは、ここに配送されます。</text>
          </panel>
        </panel>
      </layout_panel>
    </layout_stack>
    <panel name="button_panel">
      <layout_stack name="button_panel_ls">
        <layout_panel name="info_btn_lp">
          <button label="プロフィール" name="info_btn" tool_tip="オブジェクトのプロフィールが表示されます。" />
        </layout_panel>
        <layout_panel name="share_btn_lp">
          <button label="共有" name="share_btn" tool_tip="インベントリアイテムを共有します。" />
        </layout_panel>
        <layout_panel name="shop_btn_lp">
          <button label="マーケットプレイス" name="shop_btn" tool_tip="マーケットプレイスのWebページを開きます。" />
          <button label="着用" name="wear_btn" tool_tip="選択したアウトフィットを着用します。" />
          <button label="再生" name="play_btn" />
          <button label="テレポート" name="teleport_btn" tool_tip="選択したエリアにてレポートします。" />
        </layout_panel>
      </layout_stack>
    </panel>
  </panel>
  <panel name="sidepanel__item_panel" label="" />
  <panel name="sidepanel__task_panel" label="" />
</panel>