<llsd>
    <map>
    <key>ambient</key>
        <array>
            <real>0.14999999105930328</real>
            <real>0.106283999979496</real>
            <real>0.14465400576591492</real>
            <real>0.14999999105930328</real>
        </array>
    <key>blue_density</key>
        <array>
            <real>0.14522500336170197</real>
            <real>0.39999699592590332</real>
            <real>0.80000197887420654</real>
            <real>1</real>
        </array>
    <key>blue_horizon</key>
        <array>
            <real>0.12999999523162842</real>
            <real>0.30000001192092896</real>
            <real>0.35131001472473145</real>
            <real>1</real>
        </array>
    <key>cloud_color</key>
        <array>
            <real>0.41999998688697815</real>
            <real>0.41999998688697815</real>
            <real>0.71999996900558472</real>
            <real>0.71999996900558472</real>
        </array>
    <key>cloud_pos_density1</key>
        <array>
            <real>0.5</real>
            <real>0.5</real>
            <real>0.68999999761581421</real>
            <real>1</real>
        </array>
    <key>cloud_pos_density2</key>
        <array>
            <real>0.5</real>
            <real>0.5</real>
            <real>0.125</real>
            <real>1</real>
        </array>
    <key>cloud_scale</key>
        <array>
            <real>0.38999998569488525</real>
            <real>0</real>
            <real>0</real>
            <real>1</real>
        </array>
    <key>cloud_scroll_rate</key>
        <array>
            <real>10.49940013885498</real>
            <real>10.01099967956543</real>
        </array>
    <key>cloud_shadow</key>
        <array>
            <real>0.32999998331069946</real>
            <real>0</real>
            <real>0</real>
            <real>1</real>
        </array>
    <key>density_multiplier</key>
        <array>
            <real>0.00031000000308267772</real>
            <real>0</real>
            <real>0</real>
            <real>1</real>
        </array>
    <key>distance_multiplier</key>
        <array>
            <real>25.5</real>
            <real>0</real>
            <real>0</real>
            <real>1</real>
        </array>
    <key>east_angle</key>
        <real>2.5132739543914795</real>
    <key>enable_cloud_scroll</key>
        <array>
            <boolean>0</boolean>
            <boolean>0</boolean>
        </array>
    <key>gamma</key>
        <array>
            <real>1.6100000143051147</real>
            <real>0</real>
            <real>0</real>
            <real>1</real>
        </array>
    <key>glow</key>
        <array>
            <real>4.6000003814697266</real>
            <real>0.0010000000474974513</real>
            <real>-0.49999997019767761</real>
            <real>1</real>
        </array>
    <key>haze_density</key>
        <array>
            <real>0.53999996185302734</real>
            <real>0</real>
            <real>0</real>
            <real>1</real>
        </array>
    <key>haze_horizon</key>
        <array>
            <real>0.34999999403953552</real>
            <real>0.19915600121021271</real>
            <real>0.19915600121021271</real>
            <real>1</real>
        </array>
    <key>lightnorm</key>
        <array>
            <real>-0.58054876327514648</real>
            <real>0.15643446147441864</real>
            <real>-0.79905658960342407</real>
            <real>0</real>
        </array>
    <key>max_y</key>
        <array>
            <real>632</real>
            <real>0</real>
            <real>0</real>
            <real>1</real>
        </array>
    <key>preset_num</key>
        <integer>21</integer>
    <key>star_brightness</key>
        <real>0.059999998658895493</real>
    <key>sun_angle</key>
        <real>0.15707962214946747</real>
    <key>sunlight_color</key>
        <array>
            <real>1.5299999713897705</real>
            <real>1.3500000238418579</real>
            <real>1.3500000238418579</real>
            <real>1.5299999713897705</real>
        </array>
    </map>
</llsd>
